{
    "Ar36": {
        "error": 0.0006905786415596295, 
        "filter_outliers_dict": {
            "filter_outliers": true, 
            "iterations": 2, 
            "std_devs": 2
        }, 
        "fit": "Parabolic", 
        "value": 0.11469550874930301
    }, 
    "Ar37": {
        "error": 0.011906771887090464, 
        "filter_outliers_dict": {
            "filter_outliers": true, 
            "iterations": 2, 
            "std_devs": 2
        }, 
        "fit": "linear", 
        "value": 28.49109933351232
    }, 
    "Ar38": {
        "error": 0.012568148483150297, 
        "filter_outliers_dict": {
            "filter_outliers": true, 
            "iterations": 2, 
            "std_devs": 2
        }, 
        "fit": "linear", 
        "value": 0.007939506002020704
    }, 
    "Ar39": {
        "error": 0.023215549289841705, 
        "filter_outliers_dict": {
            "filter_outliers": true, 
            "iterations": 2, 
            "std_devs": 2
        }, 
        "fit": "Parabolic", 
        "value": 3.7486508512532124
    }, 
    "Ar40": {
        "error": 0.020994482249188328, 
        "filter_outliers_dict": {
            "filter_outliers": true, 
            "iterations": 2, 
            "std_devs": 2
        }, 
        "fit": "Parabolic", 
        "value": 34.397490234815216
    }
}