{
    "Ar36": {
        "error": 0.0006670523624861831, 
        "filter_outliers_dict": {
            "filter_outliers": true, 
            "iterations": 2, 
            "std_devs": 2
        }, 
        "fit": "Parabolic", 
        "value": 0.09614926207857141
    }, 
    "Ar37": {
        "error": 0.015123722581935105, 
        "filter_outliers_dict": {
            "filter_outliers": true, 
            "iterations": 2, 
            "std_devs": 2
        }, 
        "fit": "linear", 
        "value": 41.59845758087293
    }, 
    "Ar38": {
        "error": 0.013553226048920402, 
        "filter_outliers_dict": {
            "filter_outliers": true, 
            "iterations": 2, 
            "std_devs": 2
        }, 
        "fit": "linear", 
        "value": 0.0073319185144957
    }, 
    "Ar39": {
        "error": 0.02183859202698171, 
        "filter_outliers_dict": {
            "filter_outliers": true, 
            "iterations": 2, 
            "std_devs": 2
        }, 
        "fit": "Parabolic", 
        "value": 6.624925026472092
    }, 
    "Ar40": {
        "error": 0.021491165632577067, 
        "filter_outliers_dict": {
            "filter_outliers": true, 
            "iterations": 2, 
            "std_devs": 2
        }, 
        "fit": "Parabolic", 
        "value": 50.99856231299154
    }
}