{
    "Ar36": {
        "error": 0.00027575577922267985, 
        "filter_outliers_dict": {
            "filter_outliers": true, 
            "iterations": 2, 
            "std_devs": 2
        }, 
        "fit": "Parabolic", 
        "value": 0.01352541640100969
    }, 
    "Ar37": {
        "error": 0.012747042934039752, 
        "filter_outliers_dict": {
            "filter_outliers": true, 
            "iterations": 2, 
            "std_devs": 2
        }, 
        "fit": "linear", 
        "value": 5.300070906182894
    }, 
    "Ar38": {
        "error": 0.01279918517051738, 
        "filter_outliers_dict": {
            "filter_outliers": true, 
            "iterations": 2, 
            "std_devs": 2
        }, 
        "fit": "linear", 
        "value": -0.05823349484144518
    }, 
    "Ar39": {
        "error": 0.022620508655476892, 
        "filter_outliers_dict": {
            "filter_outliers": true, 
            "iterations": 2, 
            "std_devs": 2
        }, 
        "fit": "Parabolic", 
        "value": 4.318083021606649
    }, 
    "Ar40": {
        "error": 0.01959014196893022, 
        "filter_outliers_dict": {
            "filter_outliers": true, 
            "iterations": 2, 
            "std_devs": 2
        }, 
        "fit": "Parabolic", 
        "value": 6.676711042542692
    }
}