{
    "AX": {
        "error": 0.010828915596434, 
        "filter_outliers_dict": {
            "filter_outliers": true, 
            "iterations": 1, 
            "std_devs": 2
        }, 
        "fit": "average", 
        "value": -0.12313171469573547
    }, 
    "H1": {
        "error": 0.011826892261115324, 
        "filter_outliers_dict": {
            "filter_outliers": true, 
            "iterations": 1, 
            "std_devs": 2
        }, 
        "fit": "average", 
        "value": -0.02511567900426934
    }, 
    "H2": {
        "error": 0.009630587491229874, 
        "filter_outliers_dict": {
            "filter_outliers": true, 
            "iterations": 1, 
            "std_devs": 2
        }, 
        "fit": "average", 
        "value": 0.004593854743847517
    }, 
    "L1": {
        "error": 0.009659513545125545, 
        "filter_outliers_dict": {
            "filter_outliers": true, 
            "iterations": 1, 
            "std_devs": 2
        }, 
        "fit": "average", 
        "value": -0.03530101179216478
    }, 
    "L2(CDD)": {
        "error": 5.384569581013041e-06, 
        "filter_outliers_dict": {
            "filter_outliers": true, 
            "iterations": 1, 
            "std_devs": 2
        }, 
        "fit": "average", 
        "value": 2.5535463818629237e-05
    }
}