{
    "Ar36": {
        "error": 0.00016996999789228975, 
        "filter_outliers_dict": {
            "filter_outliers": true, 
            "iterations": 2, 
            "std_devs": 2
        }, 
        "fit": "Parabolic", 
        "value": 0.0025209652304048246
    }, 
    "Ar37": {
        "error": 0.010800105362125726, 
        "filter_outliers_dict": {
            "filter_outliers": true, 
            "iterations": 2, 
            "std_devs": 2
        }, 
        "fit": "linear", 
        "value": -0.050455157892741596
    }, 
    "Ar38": {
        "error": 0.012274209259055377, 
        "filter_outliers_dict": {
            "filter_outliers": true, 
            "iterations": 2, 
            "std_devs": 2
        }, 
        "fit": "linear", 
        "value": -0.08715641285375972
    }, 
    "Ar39": {
        "error": 0.02210465335492269, 
        "filter_outliers_dict": {
            "filter_outliers": true, 
            "iterations": 2, 
            "std_devs": 2
        }, 
        "fit": "Parabolic", 
        "value": -0.02646863358866633
    }, 
    "Ar40": {
        "error": 0.0198060481044926, 
        "filter_outliers_dict": {
            "filter_outliers": true, 
            "iterations": 2, 
            "std_devs": 2
        }, 
        "fit": "Parabolic", 
        "value": 0.5767923777621107
    }
}